beamformers/__init__.py
beamformers/beamformers.py
beamformers/tests/__init__.py
beamformers/tests/test_beamformers.py
beamformers-0.5.2.dist-info/LICENSE.md
beamformers-0.5.2.dist-info/METADATA
beamformers-0.5.2.dist-info/WHEEL
beamformers-0.5.2.dist-info/top_level.txt
beamformers-0.5.2.dist-info/RECORD
