Metadata-Version: 2.1
Name: beamformers
Version: 0.5.2
Summary: Beamformers for audio source separation and speech enhancement
Home-page: https://github.com/Enny1991/beamformers
Author: Enea Ceolini (UZH Zurich)
Author-email: enea.ceolini@ini.uzh.ch
License: MIT
Platform: UNKNOWN
Requires-Dist: scipy
Requires-Dist: numpy
Requires-Dist: soundfile
